vizify/__init__.py
vizify/vizify.py
vizify-0.2.0.dist-info/licenses/LICENSE.txt
vizify-0.2.0.dist-info/METADATA
vizify-0.2.0.dist-info/WHEEL
vizify-0.2.0.dist-info/top_level.txt
vizify-0.2.0.dist-info/RECORD
